adc_toolkit/__init__.py
adc_toolkit/cli/__init__.py
adc_toolkit/cli/main.py
adc_toolkit/cli/tests/__init__.py
adc_toolkit/cli/tests/test_main.py
adc_toolkit/configuration/base/logger.yaml
adc_toolkit/configuration/base/eda/cs_parameters.yaml
adc_toolkit/configuration/base/eda/ts_parameters.yaml
adc_toolkit/configuration/local/.gitkeep
adc_toolkit/data/README.md
adc_toolkit/data/__init__.py
adc_toolkit/data/abs.py
adc_toolkit/data/catalog.py
adc_toolkit/data/default_attributes.py
adc_toolkit/data/catalogs/__init__.py
adc_toolkit/data/catalogs/kedro/__init__.py
adc_toolkit/data/catalogs/kedro/kedro_catalog.py
adc_toolkit/data/catalogs/kedro/kedro_configs.py
adc_toolkit/data/catalogs/kedro/scaffold.py
adc_toolkit/data/catalogs/kedro/templates/.gitignore
adc_toolkit/data/catalogs/kedro/templates/__init__.py
adc_toolkit/data/catalogs/kedro/templates/catalog.yml
adc_toolkit/data/catalogs/kedro/templates/credentials_template.yml
adc_toolkit/data/catalogs/kedro/templates/globals.yml
adc_toolkit/data/catalogs/kedro/tests/__init__.py
adc_toolkit/data/catalogs/kedro/tests/test_kedro_catalog.py
adc_toolkit/data/catalogs/kedro/tests/test_kedro_configs.py
adc_toolkit/data/catalogs/kedro/tests/test_scaffold.py
adc_toolkit/data/tests/__init__.py
adc_toolkit/data/tests/test_catalog.py
adc_toolkit/data/tests/test_default_attributes.py
adc_toolkit/data/validators/__init__.py
adc_toolkit/data/validators/no_validator.py
adc_toolkit/data/validators/gx/__init__.py
adc_toolkit/data/validators/gx/validator.py
adc_toolkit/data/validators/gx/batch_managers/__init__.py
adc_toolkit/data/validators/gx/batch_managers/batch_manager.py
adc_toolkit/data/validators/gx/batch_managers/batch_validation.py
adc_toolkit/data/validators/gx/batch_managers/checkpoint_manager.py
adc_toolkit/data/validators/gx/batch_managers/datasource_manager.py
adc_toolkit/data/validators/gx/batch_managers/expectation_addition_strategy.py
adc_toolkit/data/validators/gx/batch_managers/expectation_suite_lookup_strategy.py
adc_toolkit-1.1.0.dist-info/METADATA
adc_toolkit-1.1.0.dist-info/WHEEL
adc_toolkit-1.1.0.dist-info/entry_points.txt
adc_toolkit-1.1.0.dist-info/licenses/LICENCE
adc_toolkit-1.1.0.dist-info/RECORD
