Metadata-Version: 2.4
Name: adc-toolkit
Version: 1.1.0
Summary: ADC toolkit, here to help you.
Project-URL: Repository, https://github.com/ADC-Consulting/adc-toolkit
Project-URL: Documentation, https://adc-consulting.github.io/adc-toolkit/adc_toolkit.html
Author-email: Ivan <ivan.k@adc-consulting.com>, Jakob <jakob.d@adc-consulting.com>, Marc <marc@adc-consulting.com>, Martijn <martijn.b@adc-consulting.com>, Niek <niek.vdl@adc-consulting.com>, Nils <nils.j@adc-consulting.com>, Rutger <rutger.l@adc-consulting.com>, Noortje <noortje.m@adc-consulting.com>, Ron <ron.k@adc-consulting.com>
License-Expression: MIT
License-File: LICENCE
Requires-Python: <3.14,>=3.10
Requires-Dist: numpy>=2.2.2
Requires-Dist: pandas>=2.2.3
Requires-Dist: pyyaml>=6.0
Provides-Extra: dev
Requires-Dist: ipykernel>=6.13.0; extra == 'dev'
Requires-Dist: pdoc>=15.0.1; extra == 'dev'
Requires-Dist: pre-commit>=3.2.0; extra == 'dev'
Requires-Dist: pytest-cov>=3.0.0; extra == 'dev'
Requires-Dist: pytest>=7.1.2; extra == 'dev'
Requires-Dist: ruff>=0.14.0; extra == 'dev'
Provides-Extra: eda
Requires-Dist: matplotlib>=3.7.2; extra == 'eda'
Requires-Dist: statsmodels>=0.14.4; extra == 'eda'
Provides-Extra: gcp
Requires-Dist: dbt-bigquery>=1.0.0; extra == 'gcp'
Requires-Dist: gcsfs>=2023.9.2; extra == 'gcp'
Requires-Dist: google-api-core>=2.8.2; extra == 'gcp'
Requires-Dist: google-cloud-bigquery-storage>=2.13.0; extra == 'gcp'
Requires-Dist: pandas-gbq>=0.19.2; extra == 'gcp'
Provides-Extra: gx
Requires-Dist: great-expectations<1.0.0,>=0.18.2; extra == 'gx'
Provides-Extra: kedro
Requires-Dist: fastparquet>=2023.7.0; extra == 'kedro'
Requires-Dist: kedro-datasets>=9.0.0; extra == 'kedro'
Requires-Dist: kedro>=1.0.0; extra == 'kedro'
Requires-Dist: pyarrow>=22.0.0; extra == 'kedro'
Provides-Extra: logging
Requires-Dist: loguru>=0.7.2; extra == 'logging'
Provides-Extra: pandera
Requires-Dist: pandera>=0.24.0; extra == 'pandera'
Provides-Extra: preprocessing
Requires-Dist: scikit-learn>=1.5.2; extra == 'preprocessing'
Provides-Extra: spark
Requires-Dist: pyspark>=3.5.0; extra == 'spark'
Requires-Dist: zstandard>=0.25.0; extra == 'spark'
